[
  {
    "start": 0.21,
    "duraction": 5.16,
    "value": "what do you do if a liberal throws a"
  },
  {
    "start": 1.949,
    "duraction": 6.211,
    "value": "grenade at you pull out the pin and"
  },
  {
    "start": 5.37,
    "duraction": 4.47,
    "value": "throw it back okay that was super cheesy"
  },
  {
    "start": 8.16,
    "duraction": 3.09,
    "value": "what's up guys my name is Dylan wheeler"
  },
  {
    "start": 9.84,
    "duraction": 2.82,
    "value": "and today I wanted to take a quick"
  },
  {
    "start": 11.25,
    "duraction": 3.929,
    "value": "moment to breakdown the fragile"
  },
  {
    "start": 12.66,
    "duraction": 4.14,
    "value": "psychology of liberals but before we do"
  },
  {
    "start": 15.179,
    "duraction": 3.781,
    "value": "that please give this video a thumbs up"
  },
  {
    "start": 16.8,
    "duraction": 4.41,
    "value": "hit subscribe if you haven't already and"
  },
  {
    "start": 18.96,
    "duraction": 4.17,
    "value": "let's get this thing rolling okay let's"
  },
  {
    "start": 21.21,
    "duraction": 3.78,
    "value": "start this off with a quick question how"
  },
  {
    "start": 23.13,
    "duraction": 4.229,
    "value": "many of you talking to conservatives"
  },
  {
    "start": 24.99,
    "duraction": 4.289,
    "value": "here have been discriminated against for"
  },
  {
    "start": 27.359,
    "duraction": 3.391,
    "value": "voicing your support for President Trump"
  },
  {
    "start": 29.279,
    "duraction": 3.631,
    "value": "my guess is that most of you probably"
  },
  {
    "start": 30.75,
    "duraction": 3.84,
    "value": "have and if you're anything like me you"
  },
  {
    "start": 32.91,
    "duraction": 3.63,
    "value": "get discriminated against almost every"
  },
  {
    "start": 34.59,
    "duraction": 4.08,
    "value": "single day hell I've even had to defend"
  },
  {
    "start": 36.54,
    "duraction": 4.679,
    "value": "myself in fist fights for voicing my"
  },
  {
    "start": 38.67,
    "duraction": 7.08,
    "value": "support for president Trump oh by the"
  },
  {
    "start": 41.219,
    "duraction": 6.421,
    "value": "way I'm still undefeated anyways a"
  },
  {
    "start": 45.75,
    "duraction": 4.469,
    "value": "recent poll conducted by the hill backs"
  },
  {
    "start": 47.64,
    "duraction": 3.72,
    "value": "me up on this it says that 76% of"
  },
  {
    "start": 50.219,
    "duraction": 2.791,
    "value": "conservatives claim they are"
  },
  {
    "start": 51.36,
    "duraction": 4.26,
    "value": "discriminated against because of their"
  },
  {
    "start": 53.01,
    "duraction": 4.02,
    "value": "political views while only 16% of"
  },
  {
    "start": 55.62,
    "duraction": 3.509,
    "value": "liberals claim they're discriminated"
  },
  {
    "start": 57.03,
    "duraction": 4.32,
    "value": "against because of theirs those are very"
  },
  {
    "start": 59.129,
    "duraction": 3.48,
    "value": "lopsided numbers I mean do you guys"
  },
  {
    "start": 61.35,
    "duraction": 3.059,
    "value": "remember the days when conservatives"
  },
  {
    "start": 62.609,
    "duraction": 3.631,
    "value": "would go out of their way to chase down"
  },
  {
    "start": 64.409,
    "duraction": 3.96,
    "value": "on liberals harass them curse them out"
  },
  {
    "start": 66.24,
    "duraction": 4.62,
    "value": "refuse them service or even beat them up"
  },
  {
    "start": 68.369,
    "duraction": 4.32,
    "value": "for wearing an Obama t-shirt no and"
  },
  {
    "start": 70.86,
    "duraction": 3.299,
    "value": "that's because it didn't happen imagine"
  },
  {
    "start": 72.689,
    "duraction": 3.421,
    "value": "being so mentally weak and so"
  },
  {
    "start": 74.159,
    "duraction": 3.57,
    "value": "emotionally immature that a piece of"
  },
  {
    "start": 76.11,
    "duraction": 3.299,
    "value": "clothing can trigger you into a temper"
  },
  {
    "start": 77.729,
    "duraction": 4.111,
    "value": "tantrum worse than a two-year-old child"
  },
  {
    "start": 79.409,
    "duraction": 4.021,
    "value": "it's pathetic but so are their beliefs"
  },
  {
    "start": 81.84,
    "duraction": 3.569,
    "value": "and that's where a lot of this craziness"
  },
  {
    "start": 83.43,
    "duraction": 3.96,
    "value": "comes from I mean how can any sane"
  },
  {
    "start": 85.409,
    "duraction": 3.901,
    "value": "person support a party that believes in"
  },
  {
    "start": 87.39,
    "duraction": 4.32,
    "value": "illegal aliens over our own American"
  },
  {
    "start": 89.31,
    "duraction": 4.739,
    "value": "citizens open borders over our own"
  },
  {
    "start": 91.71,
    "duraction": 5.1,
    "value": "national security socialism over"
  },
  {
    "start": 94.049,
    "duraction": 4.831,
    "value": "capitalism and infanticide over human"
  },
  {
    "start": 96.81,
    "duraction": 3.69,
    "value": "life you would have to be legitimately"
  },
  {
    "start": 98.88,
    "duraction": 3.48,
    "value": "brainwashed to believe any of these"
  },
  {
    "start": 100.5,
    "duraction": 4.17,
    "value": "things and that's exactly what they are"
  },
  {
    "start": 102.36,
    "duraction": 4.32,
    "value": "brainwashed the fullest but the"
  },
  {
    "start": 104.67,
    "duraction": 4.229,
    "value": "mainstream media who uses them as pawns"
  },
  {
    "start": 106.68,
    "duraction": 4.259,
    "value": "to further their globalist agenda these"
  },
  {
    "start": 108.899,
    "duraction": 4.711,
    "value": "people are zombies but that's because"
  },
  {
    "start": 110.939,
    "duraction": 4.591,
    "value": "the mainstream media aka the fake news"
  },
  {
    "start": 113.61,
    "duraction": 3.84,
    "value": "media is I and president Trump and"
  },
  {
    "start": 115.53,
    "duraction": 4.379,
    "value": "others like to call them consist of only"
  },
  {
    "start": 117.45,
    "duraction": 5.07,
    "value": "six corporations won by globalist"
  },
  {
    "start": 119.909,
    "duraction": 5.1,
    "value": "billionaires who control over 90% of"
  },
  {
    "start": 122.52,
    "duraction": 5.22,
    "value": "what we get to read watch and listen to"
  },
  {
    "start": 125.009,
    "duraction": 4.711,
    "value": "that's a huge number and especially when"
  },
  {
    "start": 127.74,
    "duraction": 4.139,
    "value": "they're giving President Trump over 90%"
  },
  {
    "start": 129.72,
    "duraction": 3.54,
    "value": "negative news coverage now combine that"
  },
  {
    "start": 131.879,
    "duraction": 1.711,
    "value": "with their different ways of dumbing us"
  },
  {
    "start": 133.26,
    "duraction": 2.309,
    "value": "down"
  },
  {
    "start": 133.59,
    "duraction": 3.33,
    "value": "and their sinister agenda becomes a"
  },
  {
    "start": 135.569,
    "duraction": 3.061,
    "value": "little more clear they have been"
  },
  {
    "start": 136.92,
    "duraction": 4.08,
    "value": "poisoning our bodies and minds through"
  },
  {
    "start": 138.63,
    "duraction": 5.04,
    "value": "the harmful chemicals in our food water"
  },
  {
    "start": 141.0,
    "duraction": 4.23,
    "value": "air and the big pharmaceutical companies"
  },
  {
    "start": 143.67,
    "duraction": 3.3,
    "value": "who create drugs that keep us"
  },
  {
    "start": 145.23,
    "duraction": 3.81,
    "value": "perpetually sick so they can make"
  },
  {
    "start": 146.97,
    "duraction": 3.96,
    "value": "monster profits and they have total"
  },
  {
    "start": 149.04,
    "duraction": 3.99,
    "value": "control over Hollywood which is capable"
  },
  {
    "start": 150.93,
    "duraction": 4.41,
    "value": "of influencing the minds of those who"
  },
  {
    "start": 153.03,
    "duraction": 3.15,
    "value": "idolize false prophets but you know what"
  },
  {
    "start": 155.34,
    "duraction": 2.19,
    "value": "the worst part is"
  },
  {
    "start": 156.18,
    "duraction": 3.389,
    "value": "they've been dumbing down our public"
  },
  {
    "start": 157.53,
    "duraction": 4.38,
    "value": "education system in order to brainwash"
  },
  {
    "start": 159.569,
    "duraction": 4.5,
    "value": "our youth into believing the radical and"
  },
  {
    "start": 161.91,
    "duraction": 4.049,
    "value": "regressive ideas of socialism and"
  },
  {
    "start": 164.069,
    "duraction": 3.661,
    "value": "communism now you can see why waking up"
  },
  {
    "start": 165.959,
    "duraction": 3.271,
    "value": "people is so damn hard they've been"
  },
  {
    "start": 167.73,
    "duraction": 3.24,
    "value": "programmed their whole lives to believe"
  },
  {
    "start": 169.23,
    "duraction": 3.66,
    "value": "that what they learn in school or what"
  },
  {
    "start": 170.97,
    "duraction": 3.54,
    "value": "they heard on the TV is the absolute"
  },
  {
    "start": 172.89,
    "duraction": 3.12,
    "value": "truth and now they're too dumb to"
  },
  {
    "start": 174.51,
    "duraction": 2.97,
    "value": "question any of it but it makes sense"
  },
  {
    "start": 176.01,
    "duraction": 2.759,
    "value": "when you think about it most people"
  },
  {
    "start": 177.48,
    "duraction": 3.45,
    "value": "these days get their news from social"
  },
  {
    "start": 178.769,
    "duraction": 4.041,
    "value": "media you go on your snapchat they have"
  },
  {
    "start": 180.93,
    "duraction": 4.5,
    "value": "a curated section full of liberal bias"
  },
  {
    "start": 182.81,
    "duraction": 3.37,
    "value": "slanting articles you go on Twitter it's"
  },
  {
    "start": 185.43,
    "duraction": 2.58,
    "value": "the same thing"
  },
  {
    "start": 186.18,
    "duraction": 3.809,
    "value": "Facebook same thing you turn on the news"
  },
  {
    "start": 188.01,
    "duraction": 3.9,
    "value": "stations almost all of them liberal bias"
  },
  {
    "start": 189.989,
    "duraction": 3.36,
    "value": "slants so it's kind of hard not to"
  },
  {
    "start": 191.91,
    "duraction": 3.27,
    "value": "believe it when it's constantly being"
  },
  {
    "start": 193.349,
    "duraction": 3.511,
    "value": "thrown in your face and that's exactly"
  },
  {
    "start": 195.18,
    "duraction": 3.51,
    "value": "why I think liberals become so defensive"
  },
  {
    "start": 196.86,
    "duraction": 3.54,
    "value": "when talking about politics they deal"
  },
  {
    "start": 198.69,
    "duraction": 3.6,
    "value": "with the classic case of cognitive"
  },
  {
    "start": 200.4,
    "duraction": 3.3,
    "value": "dissonance this is what happens when you"
  },
  {
    "start": 202.29,
    "duraction": 3.87,
    "value": "are presented with facts and evidence"
  },
  {
    "start": 203.7,
    "duraction": 3.87,
    "value": "that contradict your current beliefs and"
  },
  {
    "start": 206.16,
    "duraction": 3.419,
    "value": "since conservatives tend to deal with"
  },
  {
    "start": 207.57,
    "duraction": 3.87,
    "value": "facts logic and reasoning a set of"
  },
  {
    "start": 209.579,
    "duraction": 3.211,
    "value": "emotions liberals end up being on the"
  },
  {
    "start": 211.44,
    "duraction": 3.629,
    "value": "other side feeling very stressed"
  },
  {
    "start": 212.79,
    "duraction": 3.87,
    "value": "confused and overwhelmed which can"
  },
  {
    "start": 215.069,
    "duraction": 3.211,
    "value": "sometimes set them off into physical"
  },
  {
    "start": 216.66,
    "duraction": 3.18,
    "value": "aggression towards you because they're"
  },
  {
    "start": 218.28,
    "duraction": 3.329,
    "value": "not ready to have their false illusions"
  },
  {
    "start": 219.84,
    "duraction": 3.269,
    "value": "of reality shattered yet they would"
  },
  {
    "start": 221.609,
    "duraction": 3.0,
    "value": "rather let somebody else think for them"
  },
  {
    "start": 223.109,
    "duraction": 3.241,
    "value": "while they remain in their group think"
  },
  {
    "start": 224.609,
    "duraction": 3.421,
    "value": "echo chambers being consumed by their"
  },
  {
    "start": 226.35,
    "duraction": 3.75,
    "value": "own confirmation bias which is"
  },
  {
    "start": 228.03,
    "duraction": 3.69,
    "value": "dangerously stupid I'd rather hear an"
  },
  {
    "start": 230.1,
    "duraction": 3.18,
    "value": "uncomfortable truth and then work on"
  },
  {
    "start": 231.72,
    "duraction": 3.359,
    "value": "trying to find a solution to whatever"
  },
  {
    "start": 233.28,
    "duraction": 3.57,
    "value": "the problem is rather than hearing a"
  },
  {
    "start": 235.079,
    "duraction": 4.111,
    "value": "comfortable lie and allowing something"
  },
  {
    "start": 236.85,
    "duraction": 3.75,
    "value": "very bad to happen globalist want us to"
  },
  {
    "start": 239.19,
    "duraction": 4.079,
    "value": "fight amongst ourselves in a class"
  },
  {
    "start": 240.6,
    "duraction": 4.71,
    "value": "warfare of a race sex religion politics"
  },
  {
    "start": 243.269,
    "duraction": 3.931,
    "value": "and anything else they can in order to"
  },
  {
    "start": 245.31,
    "duraction": 3.929,
    "value": "keep us divided rather than coming"
  },
  {
    "start": 247.2,
    "duraction": 3.09,
    "value": "together as one and taking them out our"
  },
  {
    "start": 249.239,
    "duraction": 3.12,
    "value": "true enemy"
  },
  {
    "start": 250.29,
    "duraction": 3.96,
    "value": "when Patriots all over America and all"
  },
  {
    "start": 252.359,
    "duraction": 3.151,
    "value": "over the world even are aware of this"
  },
  {
    "start": 254.25,
    "duraction": 3.51,
    "value": "threat and we're tasked with the"
  },
  {
    "start": 255.51,
    "duraction": 4.229,
    "value": "challenge and the responsibility to try"
  },
  {
    "start": 257.76,
    "duraction": 3.36,
    "value": "to wake up our liberal friends and no"
  },
  {
    "start": 259.739,
    "duraction": 3.151,
    "value": "not every single one of them are going"
  },
  {
    "start": 261.12,
    "duraction": 4.14,
    "value": "to wake up even when presented with"
  },
  {
    "start": 262.89,
    "duraction": 4.17,
    "value": "concrete facts and evidence and that's"
  },
  {
    "start": 265.26,
    "duraction": 2.31,
    "value": "just something we have to accept so let"
  },
  {
    "start": 267.06,
    "duraction": 2.07,
    "value": "go"
  },
  {
    "start": 267.57,
    "duraction": 3.51,
    "value": "and leg godt we are winning this"
  },
  {
    "start": 269.13,
    "duraction": 3.63,
    "value": "unconventional style of informational"
  },
  {
    "start": 271.08,
    "duraction": 2.28,
    "value": "warfare that the world has never seen"
  },
  {
    "start": 272.76,
    "duraction": 1.98,
    "value": "before"
  },
  {
    "start": 273.36,
    "duraction": 3.06,
    "value": "and we're gonna take our country back"
  },
  {
    "start": 274.74,
    "duraction": 3.51,
    "value": "from these globalist who have sought to"
  },
  {
    "start": 276.42,
    "duraction": 3.36,
    "value": "destroy it we just need to keep shedding"
  },
  {
    "start": 278.25,
    "duraction": 3.33,
    "value": "the light on the darkness wherever we"
  },
  {
    "start": 279.78,
    "duraction": 3.54,
    "value": "find it and spreading the truth to"
  },
  {
    "start": 281.58,
    "duraction": 3.48,
    "value": "anyone who's willing to listen thanks"
  },
  {
    "start": 283.32,
    "duraction": 3.63,
    "value": "for watching my video guys I've been"
  },
  {
    "start": 285.06,
    "duraction": 3.87,
    "value": "actively engaged in politics for well"
  },
  {
    "start": 286.95,
    "duraction": 3.63,
    "value": "over three years now and one day I would"
  },
  {
    "start": 288.93,
    "duraction": 3.6,
    "value": "love to become a full-time content"
  },
  {
    "start": 290.58,
    "duraction": 3.45,
    "value": "creator but I can't do it alone so if"
  },
  {
    "start": 292.53,
    "duraction": 3.9,
    "value": "any of you would like to support my work"
  },
  {
    "start": 294.03,
    "duraction": 3.84,
    "value": "please do so by donating to my patreon"
  },
  {
    "start": 296.43,
    "duraction": 3.54,
    "value": "which you can find in the link in the"
  },
  {
    "start": 297.87,
    "duraction": 4.47,
    "value": "description box and for anyone who"
  },
  {
    "start": 299.97,
    "duraction": 4.32,
    "value": "donates $5 or more I will personally"
  },
  {
    "start": 302.34,
    "duraction": 4.47,
    "value": "follow you back on Twitter or Instagram"
  },
  {
    "start": 304.29,
    "duraction": 4.56,
    "value": "or both if you have both as my way of"
  },
  {
    "start": 306.81,
    "duraction": 4.05,
    "value": "saying thank you I appreciate it guys"
  },
  {
    "start": 308.85,
    "duraction": 5.06,
    "value": "god bless take care and I'll be back"
  },
  {
    "start": 310.86,
    "duraction": 3.05,
    "value": "soon with more"
  }
]